[
    {
        "idcity": "233757",
        "day": "2019-11-01",
        "tempday": "+7",
        "barday": "748",
        "cloudinessDAY": "малооблачно",
        "phenomenamaEl": "-",
        "Wind": "З 4м/с",
        "tempnight": "+5",
        "barnight": "749",
        "cloudinessnight": "ясно",
        "phenomenamaElnight": "-",
        "Windnight": "З 4м/с"
    },
    {
        "idcity": "233757",
        "day": "2019-11-02",
        "tempday": "+2",
        "barday": "749",
        "cloudinessDAY": "облачно",
        "phenomenamaEl": "-",
        "Wind": "З 2м/с",
        "tempnight": "+1",
        "barnight": "750",
        "cloudinessnight": "малооблачно",
        "phenomenamaElnight": "-",
        "Windnight": "З 2м/с"
    },
    {
        "idcity": "233757",
        "day": "2019-11-03",
        "tempday": "+2",
        "barday": "754",
        "cloudinessDAY": "малооблачно",
        "phenomenamaEl": "-",
        "Wind": "С 2м/с",
        "tempnight": "-1",
        "barnight": "757",
        "cloudinessnight": "малооблачно",
        "phenomenamaElnight": "-",
        "Windnight": "С 2м/с"
    },
    {
        "idcity": "233757",
        "day": "2019-11-04",
        "tempday": "+4",
        "barday": "756",
        "cloudinessDAY": "малооблачно",
        "phenomenamaEl": "-",
        "Wind": "З 4м/с",
        "tempnight": "0",
        "barnight": "756",
        "cloudinessnight": "облачно",
        "phenomenamaElnight": "-",
        "Windnight": "З 4м/с"
    },
    {
        "idcity": "233757",
        "day": "2019-11-05",
        "tempday": "+5",
        "barday": "749",
        "cloudinessDAY": "ясно",
        "phenomenamaEl": "-",
        "Wind": "Ш",
        "tempnight": "-6",
        "barnight": "749",
        "cloudinessnight": "ясно",
        "phenomenamaElnight": "-",
        "Windnight": "Ш"
    },
    {
        "idcity": "233757",
        "day": "2019-11-06",
        "tempday": "+2",
        "barday": "749",
        "cloudinessDAY": "малооблачно",
        "phenomenamaEl": "-",
        "Wind": "СЗ 3м/с",
        "tempnight": "-3",
        "barnight": "749",
        "cloudinessnight": "малооблачно",
        "phenomenamaElnight": "-",
        "Windnight": "СЗ 3м/с"
    },
    {
        "idcity": "233757",
        "day": "2019-11-07",
        "tempday": "-5",
        "barday": "748",
        "cloudinessDAY": "малооблачно",
        "phenomenamaEl": "-",
        "Wind": "СЗ 4м/с",
        "tempnight": "-10",
        "barnight": "750",
        "cloudinessnight": "малооблачно",
        "phenomenamaElnight": "-",
        "Windnight": "СЗ 4м/с"
    },
    {
        "idcity": "233757",
        "day": "2019-11-08",
        "tempday": "-6",
        "barday": "751",
        "cloudinessDAY": "малооблачно",
        "phenomenamaEl": "-",
        "Wind": "З 3м/с",
        "tempnight": "-10",
        "barnight": "753",
        "cloudinessnight": "облачно",
        "phenomenamaElnight": "-",
        "Windnight": "З 3м/с"
    },
    {
        "idcity": "233757",
        "day": "2019-11-09",
        "tempday": "-3",
        "barday": "752",
        "cloudinessDAY": "ясно",
        "phenomenamaEl": "-",
        "Wind": "СЗ 3м/с",
        "tempnight": "-12",
        "barnight": "753",
        "cloudinessnight": "ясно",
        "phenomenamaElnight": "-",
        "Windnight": "СЗ 3м/с"
    },
    {
        "idcity": "233757",
        "day": "2019-11-10",
        "tempday": "+2",
        "barday": "750",
        "cloudinessDAY": "ясно",
        "phenomenamaEl": "-",
        "Wind": "З 1м/с",
        "tempnight": "-12",
        "barnight": "752",
        "cloudinessnight": "ясно",
        "phenomenamaElnight": "-",
        "Windnight": "З 1м/с"
    },
    {
        "idcity": "233757",
        "day": "2019-11-11",
        "tempday": "+2",
        "barday": "748",
        "cloudinessDAY": "пасмурно",
        "phenomenamaEl": "-",
        "Wind": "ЮЗ 1м/с",
        "tempnight": "-3",
        "barnight": "747",
        "cloudinessnight": "малооблачно",
        "phenomenamaElnight": "-",
        "Windnight": "ЮЗ 1м/с"
    },
    {
        "idcity": "233757",
        "day": "2019-11-12",
        "tempday": "0",
        "barday": "750",
        "cloudinessDAY": "малооблачно",
        "phenomenamaEl": "-",
        "Wind": "З 5м/с",
        "tempnight": "-4",
        "barnight": "753",
        "cloudinessnight": "ясно",
        "phenomenamaElnight": "-",
        "Windnight": "З 5м/с"
    },
    {
        "idcity": "233757",
        "day": "2019-11-13",
        "tempday": "0",
        "barday": "752",
        "cloudinessDAY": "малооблачно",
        "phenomenamaEl": "-",
        "Wind": "Ш",
        "tempnight": "-6",
        "barnight": "749",
        "cloudinessnight": "пасмурно",
        "phenomenamaElnight": "-",
        "Windnight": "Ш"
    },
    {
        "idcity": "233757",
        "day": "2019-11-14",
        "tempday": "-8",
        "barday": "736",
        "cloudinessDAY": "пасмурно",
        "phenomenamaEl": "-",
        "Wind": "Ю 3м/с",
        "tempnight": "-12",
        "barnight": "738",
        "cloudinessnight": "малооблачно",
        "phenomenamaElnight": "-",
        "Windnight": "Ю 3м/с"
    },
    {
        "idcity": "233757",
        "day": "2019-11-15",
        "tempday": "-13",
        "barday": "738",
        "cloudinessDAY": "малооблачно",
        "phenomenamaEl": "-",
        "Wind": "ЮЗ 4м/с",
        "tempnight": "-15",
        "barnight": "741",
        "cloudinessnight": "пасмурно",
        "phenomenamaElnight": "-",
        "Windnight": "ЮЗ 4м/с"
    },
    {
        "idcity": "233757",
        "day": "2019-11-16",
        "tempday": "-12",
        "barday": "748",
        "cloudinessDAY": "малооблачно",
        "phenomenamaEl": "-",
        "Wind": "З 3м/с",
        "tempnight": "-13",
        "barnight": "749",
        "cloudinessnight": "облачно",
        "phenomenamaElnight": "-",
        "Windnight": "З 3м/с"
    },
    {
        "idcity": "233757",
        "day": "2019-11-17",
        "tempday": "-6",
        "barday": "757",
        "cloudinessDAY": "малооблачно",
        "phenomenamaEl": "-",
        "Wind": "ЮЗ 3м/с",
        "tempnight": "-8",
        "barnight": "761",
        "cloudinessnight": "облачно",
        "phenomenamaElnight": "-",
        "Windnight": "ЮЗ 3м/с"
    },
    {
        "idcity": "233757",
        "day": "2019-11-18",
        "tempday": "-12",
        "barday": "754",
        "cloudinessDAY": "пасмурно",
        "phenomenamaEl": "снег",
        "Wind": "СВ 1м/с",
        "tempnight": "-9",
        "barnight": "746",
        "cloudinessnight": "пасмурно",
        "phenomenamaElnight": "снег",
        "Windnight": "СВ 1м/с"
    },
    {
        "idcity": "233757",
        "day": "2019-11-19",
        "tempday": "-6",
        "barday": "741",
        "cloudinessDAY": "пасмурно",
        "phenomenamaEl": "снег",
        "Wind": "В 2м/с",
        "tempnight": "-6",
        "barnight": "743",
        "cloudinessnight": "пасмурно",
        "phenomenamaElnight": "снег",
        "Windnight": "В 2м/с"
    },
    {
        "idcity": "233757",
        "day": "2019-11-20",
        "tempday": "-5",
        "barday": "755",
        "cloudinessDAY": "малооблачно",
        "phenomenamaEl": "-",
        "Wind": "СЗ 2м/с",
        "tempnight": "-10",
        "barnight": "758",
        "cloudinessnight": "ясно",
        "phenomenamaElnight": "-",
        "Windnight": "СЗ 2м/с"
    },
    {
        "idcity": "233757",
        "day": "2019-11-21",
        "tempday": "-6",
        "barday": "760",
        "cloudinessDAY": "ясно",
        "phenomenamaEl": "-",
        "Wind": "З 2м/с",
        "tempnight": "-13",
        "barnight": "762",
        "cloudinessnight": "ясно",
        "phenomenamaElnight": "-",
        "Windnight": "З 2м/с"
    },
    {
        "idcity": "233757",
        "day": "2019-11-22",
        "tempday": "-9",
        "barday": "765",
        "cloudinessDAY": "пасмурно",
        "phenomenamaEl": "-",
        "Wind": "Ш",
        "tempnight": "-17",
        "barnight": "765",
        "cloudinessnight": "малооблачно",
        "phenomenamaElnight": "-",
        "Windnight": "Ш"
    },
    {
        "idcity": "233757",
        "day": "2019-11-23",
        "tempday": "-2",
        "barday": "752",
        "cloudinessDAY": "малооблачно",
        "phenomenamaEl": "-",
        "Wind": "Ш",
        "tempnight": "-6",
        "barnight": "751",
        "cloudinessnight": "малооблачно",
        "phenomenamaElnight": "-",
        "Windnight": "Ш"
    },
    {
        "idcity": "233757",
        "day": "2019-11-24",
        "tempday": "-2",
        "barday": "755",
        "cloudinessDAY": "облачно",
        "phenomenamaEl": "-",
        "Wind": "З 3м/с",
        "tempnight": "-8",
        "barnight": "756",
        "cloudinessnight": "малооблачно",
        "phenomenamaElnight": "-",
        "Windnight": "З 3м/с"
    },
    {
        "idcity": "233757",
        "day": "2019-11-25",
        "tempday": "-9",
        "barday": "758",
        "cloudinessDAY": "ясно",
        "phenomenamaEl": "-",
        "Wind": "З 2м/с",
        "tempnight": "-17",
        "barnight": "761",
        "cloudinessnight": "ясно",
        "phenomenamaElnight": "-",
        "Windnight": "З 2м/с"
    },
    {
        "idcity": "233757",
        "day": "2019-11-26",
        "tempday": "-9",
        "barday": "763",
        "cloudinessDAY": "малооблачно",
        "phenomenamaEl": "-",
        "Wind": "Ш",
        "tempnight": "-19",
        "barnight": "762",
        "cloudinessnight": "малооблачно",
        "phenomenamaElnight": "-",
        "Windnight": "Ш"
    },
    {
        "idcity": "233757",
        "day": "2019-11-27",
        "tempday": "-6",
        "barday": "755",
        "cloudinessDAY": "малооблачно",
        "phenomenamaEl": "-",
        "Wind": "З 1м/с",
        "tempnight": "-12",
        "barnight": "759",
        "cloudinessnight": "пасмурно",
        "phenomenamaElnight": "-",
        "Windnight": "З 1м/с"
    },
    {
        "idcity": "233757",
        "day": "2019-11-28",
        "tempday": "-13",
        "barday": "761",
        "cloudinessDAY": "ясно",
        "phenomenamaEl": "-",
        "Wind": "З 2м/с",
        "tempnight": "-21",
        "barnight": "761",
        "cloudinessnight": "малооблачно",
        "phenomenamaElnight": "-",
        "Windnight": "З 2м/с"
    },
    {
        "idcity": "233757",
        "day": "2019-11-29",
        "tempday": "-9",
        "barday": "759",
        "cloudinessDAY": "ясно",
        "phenomenamaEl": "-",
        "Wind": "В 1м/с",
        "tempnight": "-13",
        "barnight": "760",
        "cloudinessnight": "ясно",
        "phenomenamaElnight": "-",
        "Windnight": "В 1м/с"
    },
    {
        "idcity": "233757",
        "day": "2019-11-30",
        "tempday": "-7",
        "barday": "759",
        "cloudinessDAY": "ясно",
        "phenomenamaEl": "-",
        "Wind": "ЮЗ 1м/с",
        "tempnight": "-20",
        "barnight": "760",
        "cloudinessnight": "ясно",
        "phenomenamaElnight": "-",
        "Windnight": "ЮЗ 1м/с"
    }
]